lmterminal/__init__.py
lmterminal/cli.py
lmterminal/gpt_integration.py
lmterminal/lib.py
lmterminal/templates.py
lmterminal-0.0.43.dist-info/licenses/LICENSE
lmterminal-0.0.43.dist-info/METADATA
lmterminal-0.0.43.dist-info/WHEEL
lmterminal-0.0.43.dist-info/entry_points.txt
lmterminal-0.0.43.dist-info/top_level.txt
lmterminal-0.0.43.dist-info/RECORD
