Metadata-Version: 2.4
Name: LMterminal
Version: 0.0.43
Summary: Interact with OpenAI's models from the comfort of your terminal.
Home-page: https://github.com/sderev/lmterminal
Author: Sébastien De Revière
License: Apache Licence, Version 2.0
Project-URL: Documentation, https://github.com/sderev/lmterminal
Project-URL: Issues, http://github.com/sderev/lmterminal/issues
Project-URL: Changelog, https://github.com/sderev/lmterminal/releases
Requires-Python: >=3.8
License-File: LICENSE
Requires-Dist: click
Requires-Dist: click_default_group
Requires-Dist: openai<1.0
Requires-Dist: PyYAML
Requires-Dist: rich
Requires-Dist: tiktoken
Dynamic: author
Dynamic: description
Dynamic: description-content-type
Dynamic: home-page
Dynamic: license
Dynamic: license-file
Dynamic: project-url
Dynamic: requires-dist
Dynamic: requires-python
Dynamic: summary
